mockbuster/__init__.py
mockbuster/cli.py
mockbuster/core.py
mockbuster/mcp_server.py
mockbuster/py.typed
mockbuster-0.1.1.dist-info/METADATA
mockbuster-0.1.1.dist-info/WHEEL
mockbuster-0.1.1.dist-info/entry_points.txt
mockbuster-0.1.1.dist-info/RECORD
