Metadata-Version: 2.4
Name: mockbuster
Version: 0.1.1
Summary: Python project: mockbuster
Author-email: benomahony <bomarni@googlemail.com>
License: MIT
Requires-Python: >=3.12
Requires-Dist: mcp>=1.0.0
Requires-Dist: rich>=13.0.0
Requires-Dist: typer>=0.12.0
Provides-Extra: dev
Requires-Dist: bandit>=1.7.0; extra == 'dev'
Requires-Dist: basedpyright>=1.10.0; extra == 'dev'
Requires-Dist: bump-my-version>=0.30.0; extra == 'dev'
Requires-Dist: cliqa>=0.1.0; extra == 'dev'
Requires-Dist: deptry>=0.12.0; extra == 'dev'
Requires-Dist: pre-commit>=3.6.0; extra == 'dev'
Requires-Dist: pytest-cov>=6.0.0; extra == 'dev'
Requires-Dist: pytest-examples>=0.0.10; extra == 'dev'
Requires-Dist: pytest>=8.0.0; extra == 'dev'
Requires-Dist: ruff>=0.3.0; extra == 'dev'
Requires-Dist: vulture>=2.11; extra == 'dev'
Requires-Dist: zensical>=0.0.20; extra == 'dev'
